.coveragerc
.gitignore
.gitlab-ci.yml
AUTHORS.rst
CHANGELOG.rst
LICENSE.txt
README.rst
requirements.txt
setup.cfg
setup.py
docs/Makefile
docs/authors.rst
docs/changelog.rst
docs/conf.py
docs/index.rst
docs/license.rst
docs/_static/.gitignore
src/dld/__init__.py
src/dld/dld.py
src/dld.egg-info/PKG-INFO
src/dld.egg-info/SOURCES.txt
src/dld.egg-info/dependency_links.txt
src/dld.egg-info/not-zip-safe
src/dld.egg-info/requires.txt
src/dld.egg-info/top_level.txt
tests/conftest.py
tests/test_skeleton.py